{"cameraMode":{"drawMode":0,"name":"Shaded","section":"Shading Mode"},"sceneLighting":true,"audioPlay":false,"sceneViewState":{"showFog":true,"showMaterialUpdate":false,"showSkybox":true,"showFlares":true,"showImageEffects":true,"showParticleSystems":true},"in2DMode":false,"pivot":{"x":0.20231300592422486,"y":-2.5904462337493898,"z":0.1627456396818161},"rotation":{"x":-0.6862428784370422,"y":-0.001747736125253141,"z":0.0016490921843796969,"w":-0.7273737788200378},"size":3.886850595474243,"orthographic":false}